djangocommand_client/__init__.py
djangocommand_client-0.0.2.dist-info/METADATA
djangocommand_client-0.0.2.dist-info/WHEEL
djangocommand_client-0.0.2.dist-info/RECORD
